{
  "roots": [
    {
      "key": "it9t5bf108xpxl99mfuyk2q",
      "title": "News",
      "icon": null,
      "hasTitleNumberOutlined": false,
      "vaultName": "test",
      "children": [
        {
          "key": "zjgsnmrz8s9dvlcrg7femb0",
          "title": "child",
          "icon": null,
          "hasTitleNumberOutlined": false,
          "vaultName": "test",
          "children": []
        }
      ]
    }
  ],
  "child2parent": {
    "it9t5bf108xpxl99mfuyk2q": null,
    "zjgsnmrz8s9dvlcrg7femb0": "it9t5bf108xpxl99mfuyk2q"
  },
  "notesLabelById": {
    "it9t5bf108xpxl99mfuyk2q": "News",
    "zjgsnmrz8s9dvlcrg7femb0": "child"
  }
}
